{
  "type": "cdl",
  "project": "adsd/adart3",
  "source": "http://oracc.org/adsd/adart3",
  "license": "This data is released under the CC0 license",
  "license-url": "https://creativecommons.org/publicdomain/zero/1.0/",
  "more-info": "http://oracc.org/doc/opendata/",
  "UTC-timestamp": "2019-05-31T08:26:35",
  "textid": "X300932",
  "cdl": [
    {
      "node": "c",
      "type": "text",
      "id": "X300932.U0",
      "cdl": [
        {
          "node": "d",
          "type": "object",
          "ref": ""
        },
        {
          "node": "d",
          "subtype": "obverse",
          "type": "obverse",
          "ref": "X300932.o.1",
          "label": "o"
        },
        {
          "node": "c",
          "type": "discourse",
          "subtype": "body",
          "id": "X300932.U1",
          "cdl": [
            {
              "node": "c",
              "type": "sentence",
              "implicit": "yes",
              "id": "X300932.U2",
              "label": "o 1' - o 10'",
              "cdl": [
                {
                  "node": "d",
                  "type": "line-start",
                  "ref": "X300932.2",
                  "n": "1'",
                  "label": "o 1'"
                },
                {
                  "node": "l",
                  "frag": "[...]",
                  "id": "X300932.l03a44",
                  "ref": "X300932.2.1",
                  "inst": "u",
                  "f": {
                    "lang": "akk",
                    "form": "x",
                    "delim": "",
                    "gdl": [
                      {
                        "x": "ellipsis",
                        "id": "X300932.2.1.0",
                        "breakStart": "1",
                        "break": "missing",
                        "o": "]",
                        "breakEnd": "X300932.2.1.0"
                      }
                    ],
                    "pos": "u"
                  }
                },
                {
                  "node": "l",
                  "frag": "⸢x⸣",
                  "id": "X300932.l03a45",
                  "ref": "X300932.2.2",
                  "inst": "u",
                  "f": {
                    "lang": "akk",
                    "form": "x",
                    "delim": "",
                    "gdl": [
                      {
                        "v": "x",
                        "id": "X300932.2.2.0",
                        "break": "damaged",
                        "ho": "1",
                        "hc": "1"
                      }
                    ],
                    "pos": "u"
                  }
                },
                {
                  "node": "l",
                  "frag": "[...]",
                  "id": "X300932.l03a46",
                  "ref": "X300932.2.3",
                  "inst": "u",
                  "f": {
                    "lang": "akk",
                    "form": "x",
                    "gdl": [
                      {
                        "x": "ellipsis",
                        "id": "X300932.2.3.0",
                        "breakStart": "1",
                        "break": "missing",
                        "o": "]",
                        "breakEnd": "X300932.2.3.0"
                      }
                    ],
                    "pos": "u"
                  }
                },
                {
                  "node": "d",
                  "type": "line-start",
                  "ref": "X300932.3",
                  "n": "2'",
                  "label": "o 2'"
                },
                {
                  "node": "l",
                  "frag": "[...]",
                  "id": "X300932.l03a47",
                  "ref": "X300932.3.1",
                  "inst": "u",
                  "f": {
                    "lang": "akk",
                    "form": "x",
                    "delim": "",
                    "gdl": [
                      {
                        "x": "ellipsis",
                        "id": "X300932.3.1.0",
                        "breakStart": "1",
                        "break": "missing",
                        "o": "]",
                        "breakEnd": "X300932.3.1.0"
                      }
                    ],
                    "pos": "u"
                  }
                },
                {
                  "node": "l",
                  "frag": "⸢in⸣",
                  "id": "X300932.l03a48",
                  "ref": "X300932.3.2",
                  "inst": "ina[at]PRP",
                  "sig": "@adsd/adart3%akk:in=ina[in//at (plus numeral)]PRP'PRP$ina",
                  "f": {
                    "lang": "akk",
                    "form": "in",
                    "delim": "",
                    "gdl": [
                      {
                        "v": "in",
                        "id": "X300932.3.2.0",
                        "break": "damaged",
                        "ho": "1",
                        "hc": "1"
                      }
                    ],
                    "cf": "ina",
                    "gw": "in",
                    "sense": "at (plus numeral)",
                    "norm": "ina",
                    "pos": "PRP",
                    "epos": "PRP"
                  }
                },
                {
                  "node": "l",
                  "frag": "35",
                  "id": "X300932.l03a49",
                  "ref": "X300932.3.3",
                  "inst": "n",
                  "f": {
                    "lang": "akk",
                    "form": "35",
                    "delim": "",
                    "gdl": [
                      {
                        "n": "n",
                        "sexified": "3(u) 5(diš)",
                        "form": "35",
                        "id": "X300932.3.3.0",
                        "seq": [
                          {
                            "r": "35"
                          }
                        ]
                      }
                    ],
                    "pos": "n"
                  }
                },
                {
                  "node": "c",
                  "type": "phrase",
                  "tag": "phr",
                  "id": "X300932.U4",
                  "ref": "X300932.ls00000",
                  "cdl": [
                    {
                      "node": "l",
                      "frag": "GE₆",
                      "id": "X300932.l03a4a",
                      "ref": "X300932.3.4",
                      "inst": "mūšu[night]N",
                      "sig": "@adsd/adart3%akk:GE₆=mūšu[night//night]N'N$mūšu",
                      "f": {
                        "lang": "akk",
                        "form": "GE₆",
                        "delim": "",
                        "gdl": [
                          {
                            "gg": "logo",
                            "gdl_type": "logo",
                            "group": [
                              {
                                "s": "GE₆",
                                "id": "X300932.3.4.0",
                                "role": "logo",
                                "logolang": "sux"
                              }
                            ]
                          }
                        ],
                        "cf": "mūšu",
                        "gw": "night",
                        "sense": "night",
                        "norm": "mūšu",
                        "pos": "N",
                        "epos": "N"
                      }
                    },
                    {
                      "node": "l",
                      "frag": "GIN",
                      "id": "X300932.l03a4b",
                      "ref": "X300932.3.5",
                      "inst": "alāku[go]V",
                      "sig": "@adsd/adart3%akk:GIN=alāku[go//go]V'V$alāku",
                      "f": {
                        "lang": "akk",
                        "form": "GIN",
                        "delim": "",
                        "gdl": [
                          {
                            "gg": "logo",
                            "gdl_type": "logo",
                            "group": [
                              {
                                "s": "GIN",
                                "id": "X300932.3.5.0",
                                "role": "logo",
                                "logolang": "sux"
                              }
                            ]
                          }
                        ],
                        "cf": "alāku",
                        "gw": "go",
                        "sense": "go",
                        "norm": "alāku",
                        "pos": "V",
                        "epos": "V"
                      }
                    }
                  ]
                },
                {
                  "node": "l",
                  "frag": "14",
                  "id": "X300932.l03a4c",
                  "ref": "X300932.3.6",
                  "inst": "n",
                  "f": {
                    "lang": "akk",
                    "form": "14",
                    "delim": "",
                    "gdl": [
                      {
                        "n": "n",
                        "sexified": "1(u) 4(diš)",
                        "form": "14",
                        "id": "X300932.3.6.0",
                        "break": "damaged",
                        "queried": "1",
                        "ho": "1",
                        "hc": "1",
                        "seq": [
                          {
                            "r": "14"
                          }
                        ]
                      }
                    ],
                    "pos": "n"
                  }
                },
                {
                  "node": "l",
                  "frag": "[...]",
                  "id": "X300932.l03a4d",
                  "ref": "X300932.3.7",
                  "inst": "u",
                  "f": {
                    "lang": "akk",
                    "form": "x",
                    "gdl": [
                      {
                        "x": "ellipsis",
                        "id": "X300932.3.7.0",
                        "breakStart": "1",
                        "break": "missing",
                        "o": "]",
                        "breakEnd": "X300932.3.7.0"
                      }
                    ],
                    "pos": "u"
                  }
                },
                {
                  "node": "d",
                  "type": "line-start",
                  "ref": "X300932.4",
                  "n": "3'",
                  "label": "o 3'"
                },
                {
                  "node": "l",
                  "frag": "[...]",
                  "id": "X300932.l03a4e",
                  "ref": "X300932.4.1",
                  "inst": "u",
                  "f": {
                    "lang": "akk",
                    "form": "x",
                    "delim": "",
                    "gdl": [
                      {
                        "x": "ellipsis",
                        "id": "X300932.4.1.0",
                        "breakStart": "1",
                        "break": "missing",
                        "o": "]",
                        "breakEnd": "X300932.4.1.0"
                      }
                    ],
                    "pos": "u"
                  }
                },
                {
                  "node": "l",
                  "frag": "in",
                  "id": "X300932.l03a4f",
                  "ref": "X300932.4.2",
                  "inst": "ina[around (day x)]PRP",
                  "sig": "@adsd/adart3%akk:in=ina[in//around (day x)]PRP'PRP$ina",
                  "f": {
                    "lang": "akk",
                    "form": "in",
                    "delim": "",
                    "gdl": [
                      {
                        "v": "in",
                        "id": "X300932.4.2.0"
                      }
                    ],
                    "cf": "ina",
                    "gw": "in",
                    "sense": "around (day x)",
                    "norm": "ina",
                    "pos": "PRP",
                    "epos": "PRP"
                  }
                },
                {
                  "node": "l",
                  "frag": "18",
                  "id": "X300932.l03a50",
                  "ref": "X300932.4.3",
                  "inst": "n",
                  "f": {
                    "lang": "akk",
                    "form": "18",
                    "delim": "",
                    "gdl": [
                      {
                        "n": "n",
                        "sexified": "1(u) 8(diš)",
                        "form": "18",
                        "id": "X300932.4.3.0",
                        "seq": [
                          {
                            "r": "18"
                          }
                        ]
                      }
                    ],
                    "pos": "n"
                  }
                },
                {
                  "node": "l",
                  "frag": "{mul₂}KAK.BAN",
                  "id": "X300932.l03a51",
                  "ref": "X300932.4.4",
                  "inst": "Šiltāhu[Sirius]CN",
                  "sig": "@adsd/adart3%akk:{MUL₂}KAK.BAN=Šiltāhu[Sirius//Sirius]CN'CN$Šiltāhu",
                  "f": {
                    "lang": "akk",
                    "form": "{MUL₂}KAK.BAN",
                    "delim": "",
                    "gdl": [
                      {
                        "gg": "logo",
                        "gdl_type": "logo",
                        "group": [
                          {
                            "det": "semantic",
                            "pos": "pre",
                            "seq": [
                              {
                                "gg": "logo",
                                "gdl_type": "logo",
                                "group": [
                                  {
                                    "s": "MUL₂",
                                    "id": "X300932.4.4.0",
                                    "role": "logo",
                                    "logolang": "sux"
                                  }
                                ]
                              }
                            ]
                          },
                          {
                            "s": "KAK",
                            "id": "X300932.4.4.1",
                            "role": "logo",
                            "logolang": "sux",
                            "delim": "."
                          },
                          {
                            "s": "BAN",
                            "id": "X300932.4.4.2",
                            "role": "logo",
                            "logolang": "sux"
                          }
                        ]
                      }
                    ],
                    "cf": "Šiltāhu",
                    "gw": "Sirius",
                    "sense": "Sirius",
                    "norm": "Šiltāhu",
                    "pos": "CN",
                    "epos": "CN"
                  }
                },
                {
                  "node": "l",
                  "frag": "IGI",
                  "id": "X300932.l03a52",
                  "ref": "X300932.4.5",
                  "inst": "amāru[be(come) visible]V",
                  "sig": "@adsd/adart3%akk:IGI=amāru[see//be(come) visible]V'V$amāru",
                  "f": {
                    "lang": "akk",
                    "form": "IGI",
                    "delim": "",
                    "gdl": [
                      {
                        "gg": "logo",
                        "gdl_type": "logo",
                        "group": [
                          {
                            "s": "IGI",
                            "id": "X300932.4.5.0",
                            "role": "logo",
                            "logolang": "sux"
                          }
                        ]
                      }
                    ],
                    "cf": "amāru",
                    "gw": "see",
                    "sense": "be(come) visible",
                    "norm": "amāru",
                    "pos": "V",
                    "epos": "V"
                  }
                },
                {
                  "node": "l",
                  "frag": "⸢NU",
                  "id": "X300932.l03a53",
                  "ref": "X300932.4.6",
                  "inst": "ul[not]MOD",
                  "sig": "@adsd/adart3%akk:NU=ul[not//not]MOD'MOD$ul",
                  "f": {
                    "lang": "akk",
                    "form": "NU",
                    "delim": "",
                    "gdl": [
                      {
                        "gg": "logo",
                        "gdl_type": "logo",
                        "group": [
                          {
                            "s": "NU",
                            "id": "X300932.4.6.0",
                            "break": "damaged",
                            "ho": "1",
                            "role": "logo",
                            "logolang": "sux"
                          }
                        ]
                      }
                    ],
                    "cf": "ul",
                    "gw": "not",
                    "sense": "not",
                    "norm": "ul",
                    "pos": "MOD",
                    "epos": "MOD"
                  }
                },
                {
                  "node": "l",
                  "frag": "PAP⸣",
                  "id": "X300932.l03a54",
                  "ref": "X300932.4.7",
                  "inst": "naṣāru[watch]V",
                  "sig": "@adsd/adart3%akk:PAP=naṣāru[guard//watch]V'V$naṣāru",
                  "f": {
                    "lang": "akk",
                    "form": "PAP",
                    "delim": "",
                    "gdl": [
                      {
                        "gg": "logo",
                        "gdl_type": "logo",
                        "group": [
                          {
                            "s": "PAP",
                            "id": "X300932.4.7.0",
                            "break": "damaged",
                            "role": "logo",
                            "logolang": "sux",
                            "hc": "1"
                          }
                        ]
                      }
                    ],
                    "cf": "naṣāru",
                    "gw": "guard",
                    "sense": "watch",
                    "norm": "naṣāru",
                    "pos": "V",
                    "epos": "V"
                  }
                },
                {
                  "node": "l",
                  "frag": "[...]",
                  "id": "X300932.l03a55",
                  "ref": "X300932.4.8",
                  "inst": "u",
                  "f": {
                    "lang": "akk",
                    "form": "x",
                    "gdl": [
                      {
                        "x": "ellipsis",
                        "id": "X300932.4.8.0",
                        "breakStart": "1",
                        "break": "missing",
                        "o": "]",
                        "breakEnd": "X300932.4.8.0"
                      }
                    ],
                    "pos": "u"
                  }
                },
                {
                  "node": "d",
                  "type": "line-start",
                  "ref": "X300932.5",
                  "n": "4'",
                  "label": "o 4'"
                },
                {
                  "node": "l",
                  "frag": "[...",
                  "id": "X300932.l03a56",
                  "ref": "X300932.5.1",
                  "inst": "u",
                  "f": {
                    "lang": "akk",
                    "form": "x",
                    "delim": "",
                    "gdl": [
                      {
                        "x": "ellipsis",
                        "id": "X300932.5.1.0",
                        "breakStart": "1",
                        "break": "missing",
                        "o": "["
                      }
                    ],
                    "pos": "u"
                  }
                },
                {
                  "node": "l",
                  "frag": "GE₆",
                  "id": "X300932.l03a57",
                  "ref": "X300932.5.2",
                  "inst": "mūšu[night]N",
                  "sig": "@adsd/adart3%akk:GE₆=mūšu[night//night]N'N$mūšu",
                  "f": {
                    "lang": "akk",
                    "form": "GE₆",
                    "delim": "",
                    "gdl": [
                      {
                        "gg": "logo",
                        "gdl_type": "logo",
                        "group": [
                          {
                            "s": "GE₆",
                            "id": "X300932.5.2.0",
                            "break": "missing",
                            "role": "logo",
                            "logolang": "sux"
                          }
                        ]
                      }
                    ],
                    "cf": "mūšu",
                    "gw": "night",
                    "sense": "night",
                    "norm": "mūšu",
                    "pos": "N",
                    "epos": "N"
                  }
                },
                {
                  "node": "l",
                  "frag": "22",
                  "id": "X300932.l03a58",
                  "ref": "X300932.5.3",
                  "inst": "n",
                  "f": {
                    "lang": "akk",
                    "form": "22",
                    "delim": "",
                    "gdl": [
                      {
                        "n": "n",
                        "sexified": "2(u) 2(diš)",
                        "form": "22",
                        "id": "X300932.5.3.0",
                        "break": "missing",
                        "seq": [
                          {
                            "r": "22"
                          }
                        ]
                      }
                    ],
                    "pos": "n"
                  }
                },
                {
                  "node": "l",
                  "frag": "ina",
                  "id": "X300932.l03a59",
                  "ref": "X300932.5.4",
                  "inst": "ina[in]PRP",
                  "sig": "@adsd/adart3%akk:ina=ina[in//in]PRP'PRP$ina",
                  "f": {
                    "lang": "akk",
                    "form": "ina",
                    "delim": "",
                    "gdl": [
                      {
                        "v": "ina",
                        "id": "X300932.5.4.0",
                        "break": "missing"
                      }
                    ],
                    "cf": "ina",
                    "gw": "in",
                    "sense": "in",
                    "norm": "ina",
                    "pos": "PRP",
                    "epos": "PRP"
                  }
                },
                {
                  "node": "l",
                  "frag": "ZALAG₂",
                  "id": "X300932.l03a5a",
                  "ref": "X300932.5.5",
                  "inst": "nūru[last part of the night]N",
                  "sig": "@adsd/adart3%akk:ZALAG₂=nūru[light//last part of the night]N'N$nūru",
                  "f": {
                    "lang": "akk",
                    "form": "ZALAG₂",
                    "delim": "",
                    "gdl": [
                      {
                        "gg": "logo",
                        "gdl_type": "logo",
                        "group": [
                          {
                            "s": "ZALAG₂",
                            "id": "X300932.5.5.0",
                            "break": "missing",
                            "role": "logo",
                            "logolang": "sux"
                          }
                        ]
                      }
                    ],
                    "cf": "nūru",
                    "gw": "light",
                    "sense": "last part of the night",
                    "norm": "nūru",
                    "pos": "N",
                    "epos": "N"
                  }
                },
                {
                  "node": "l",
                  "frag": "sin",
                  "id": "X300932.l03a5b",
                  "ref": "X300932.5.6",
                  "inst": "Sîn[moon]N",
                  "sig": "@adsd/adart3%akk:sin=Sîn[moon(-god)//moon]N'N$Sîn",
                  "f": {
                    "lang": "akk",
                    "form": "sin",
                    "delim": "",
                    "gdl": [
                      {
                        "v": "sin",
                        "id": "X300932.5.6.0",
                        "break": "missing"
                      }
                    ],
                    "cf": "Sîn",
                    "gw": "moon(-god)",
                    "sense": "moon",
                    "norm": "Sîn",
                    "pos": "N",
                    "epos": "N"
                  }
                },
                {
                  "node": "l",
                  "frag": "x",
                  "id": "X300932.l03a5c",
                  "ref": "X300932.5.7",
                  "inst": "u",
                  "f": {
                    "lang": "akk",
                    "form": "x",
                    "delim": "",
                    "gdl": [
                      {
                        "v": "x",
                        "id": "X300932.5.7.0",
                        "break": "missing"
                      }
                    ],
                    "pos": "u"
                  }
                },
                {
                  "node": "l",
                  "frag": "is-le₁₀",
                  "id": "X300932.l03a5d",
                  "ref": "X300932.5.8",
                  "inst": "is-le₁₀[α Tauri]CN",
                  "sig": "@adsd/adart3%akk:is-le₁₀=is-le₁₀[α Tauri//α Tauri]CN'CN$is-le₁₀",
                  "f": {
                    "lang": "akk",
                    "form": "is-le₁₀",
                    "delim": "",
                    "gdl": [
                      {
                        "v": "is",
                        "id": "X300932.5.8.0",
                        "break": "missing",
                        "delim": "-"
                      },
                      {
                        "v": "le₁₀",
                        "id": "X300932.5.8.1",
                        "break": "missing"
                      }
                    ],
                    "cf": "is-le₁₀",
                    "gw": "α Tauri",
                    "sense": "α Tauri",
                    "norm": "is-le₁₀",
                    "pos": "CN",
                    "epos": "CN"
                  }
                },
                {
                  "node": "l",
                  "frag": "n",
                  "id": "X300932.l03a5e",
                  "ref": "X300932.5.9",
                  "inst": "n",
                  "f": {
                    "lang": "akk",
                    "form": "n",
                    "delim": "",
                    "gdl": [
                      {
                        "n": "n",
                        "form": "n",
                        "id": "X300932.5.9.0",
                        "break": "missing",
                        "seq": [
                          {
                            "r": "n"
                          }
                        ]
                      }
                    ],
                    "pos": "n"
                  }
                },
                {
                  "node": "l",
                  "frag": "n]",
                  "id": "X300932.l03a5f",
                  "ref": "X300932.5.10",
                  "inst": "n",
                  "f": {
                    "lang": "akk",
                    "form": "n",
                    "delim": "",
                    "gdl": [
                      {
                        "v": "n",
                        "id": "X300932.5.10.0",
                        "break": "missing",
                        "o": "]",
                        "breakEnd": "X300932.5.1.0"
                      }
                    ],
                    "pos": "n"
                  }
                },
                {
                  "node": "l",
                  "frag": "sin",
                  "id": "X300932.l03a60",
                  "ref": "X300932.5.11",
                  "inst": "Sîn[moon]N",
                  "sig": "@adsd/adart3%akk:sin=Sîn[moon(-god)//moon]N'N$Sîn",
                  "f": {
                    "lang": "akk",
                    "form": "sin",
                    "delim": "",
                    "gdl": [
                      {
                        "v": "sin",
                        "id": "X300932.5.11.0"
                      }
                    ],
                    "cf": "Sîn",
                    "gw": "moon(-god)",
                    "sense": "moon",
                    "norm": "Sîn",
                    "pos": "N",
                    "epos": "N"
                  }
                },
                {
                  "node": "l",
                  "frag": "3",
                  "id": "X300932.l03a61",
                  "ref": "X300932.5.12",
                  "inst": "n",
                  "f": {
                    "lang": "akk",
                    "form": "3",
                    "delim": "",
                    "gdl": [
                      {
                        "n": "n",
                        "sexified": "3(diš)",
                        "form": "3",
                        "id": "X300932.5.12.0",
                        "seq": [
                          {
                            "r": "3"
                          }
                        ]
                      }
                    ],
                    "pos": "n"
                  }
                },
                {
                  "node": "l",
                  "frag": "1/2",
                  "id": "X300932.l03a62",
                  "ref": "X300932.5.13",
                  "inst": "n",
                  "f": {
                    "lang": "akk",
                    "form": "1/2",
                    "delim": "",
                    "gdl": [
                      {
                        "n": "n",
                        "sexified": "1/2(disz)",
                        "form": "1/2",
                        "id": "X300932.5.13.0",
                        "seq": [
                          {
                            "r": "1/2"
                          }
                        ]
                      }
                    ],
                    "pos": "n"
                  }
                },
                {
                  "node": "l",
                  "frag": "KUŠ₃",
                  "id": "X300932.l03a63",
                  "ref": "X300932.5.14",
                  "inst": "ammatu[unit]N",
                  "sig": "@adsd/adart3%akk:KUŠ₃=ammatu[unit//unit]N'N$ammatu",
                  "f": {
                    "lang": "akk",
                    "form": "KUŠ₃",
                    "delim": "",
                    "gdl": [
                      {
                        "gg": "logo",
                        "gdl_type": "logo",
                        "group": [
                          {
                            "s": "KUŠ₃",
                            "id": "X300932.5.14.0",
                            "role": "logo",
                            "logolang": "sux"
                          }
                        ]
                      }
                    ],
                    "cf": "ammatu",
                    "gw": "unit",
                    "sense": "unit",
                    "norm": "ammatu",
                    "pos": "N",
                    "epos": "N"
                  }
                },
                {
                  "node": "l",
                  "frag": "ana",
                  "id": "X300932.l03a64",
                  "ref": "X300932.5.15",
                  "inst": "ana[to]PRP",
                  "sig": "@adsd/adart3%akk:ana=ana[to//to]PRP'PRP$ana",
                  "f": {
                    "lang": "akk",
                    "form": "ana",
                    "delim": "",
                    "gdl": [
                      {
                        "v": "ana",
                        "id": "X300932.5.15.0"
                      }
                    ],
                    "cf": "ana",
                    "gw": "to",
                    "sense": "to",
                    "norm": "ana",
                    "pos": "PRP",
                    "epos": "PRP"
                  }
                },
                {
                  "node": "l",
                  "frag": "SI",
                  "id": "X300932.l03a65",
                  "ref": "X300932.5.16",
                  "inst": "ištānu[north]N",
                  "sig": "@adsd/adart3%akk:SI=ištānu[north//north]N'N$ištānu",
                  "f": {
                    "lang": "akk",
                    "form": "SI",
                    "delim": "",
                    "gdl": [
                      {
                        "gg": "logo",
                        "gdl_type": "logo",
                        "group": [
                          {
                            "s": "SI",
                            "id": "X300932.5.16.0",
                            "role": "logo",
                            "logolang": "sux"
                          }
                        ]
                      }
                    ],
                    "cf": "ištānu",
                    "gw": "north",
                    "sense": "north",
                    "norm": "ištānu",
                    "pos": "N",
                    "epos": "N"
                  }
                },
                {
                  "node": "l",
                  "frag": "NIM",
                  "id": "X300932.l03a66",
                  "ref": "X300932.5.17",
                  "inst": "šaqû[be(come) high]V",
                  "sig": "@adsd/adart3%akk:NIM=šaqû[be(come) high//be(come) high]V'V$šaqû",
                  "f": {
                    "lang": "akk",
                    "form": "NIM",
                    "delim": "",
                    "gdl": [
                      {
                        "gg": "logo",
                        "gdl_type": "logo",
                        "group": [
                          {
                            "s": "NIM",
                            "id": "X300932.5.17.0",
                            "role": "logo",
                            "logolang": "sux"
                          }
                        ]
                      }
                    ],
                    "cf": "šaqû",
                    "gw": "be(come) high",
                    "sense": "be(come) high",
                    "norm": "šaqû",
                    "pos": "V",
                    "epos": "V"
                  }
                },
                {
                  "node": "l",
                  "frag": "GE₆",
                  "id": "X300932.l03a67",
                  "ref": "X300932.5.18",
                  "inst": "mūšu[night]N",
                  "sig": "@adsd/adart3%akk:GE₆=mūšu[night//night]N'N$mūšu",
                  "f": {
                    "lang": "akk",
                    "form": "GE₆",
                    "delim": "",
                    "gdl": [
                      {
                        "gg": "logo",
                        "gdl_type": "logo",
                        "group": [
                          {
                            "s": "GE₆",
                            "id": "X300932.5.18.0",
                            "role": "logo",
                            "logolang": "sux"
                          }
                        ]
                      }
                    ],
                    "cf": "mūšu",
                    "gw": "night",
                    "sense": "night",
                    "norm": "mūšu",
                    "pos": "N",
                    "epos": "N"
                  }
                },
                {
                  "node": "l",
                  "frag": "23",
                  "id": "X300932.l03a68",
                  "ref": "X300932.5.19",
                  "inst": "n",
                  "f": {
                    "lang": "akk",
                    "form": "23",
                    "delim": "",
                    "gdl": [
                      {
                        "n": "n",
                        "sexified": "2(u) 3(diš)",
                        "form": "23",
                        "id": "X300932.5.19.0",
                        "seq": [
                          {
                            "r": "23"
                          }
                        ]
                      }
                    ],
                    "pos": "n"
                  }
                },
                {
                  "node": "l",
                  "frag": "ina",
                  "id": "X300932.l03a69",
                  "ref": "X300932.5.20",
                  "inst": "ina[in]PRP",
                  "sig": "@adsd/adart3%akk:ina=ina[in//in]PRP'PRP$ina",
                  "f": {
                    "lang": "akk",
                    "form": "ina",
                    "delim": "",
                    "gdl": [
                      {
                        "v": "ina",
                        "id": "X300932.5.20.0"
                      }
                    ],
                    "cf": "ina",
                    "gw": "in",
                    "sense": "in",
                    "norm": "ina",
                    "pos": "PRP",
                    "epos": "PRP"
                  }
                },
                {
                  "node": "l",
                  "frag": "ZALAG₂",
                  "id": "X300932.l03a6a",
                  "ref": "X300932.5.21",
                  "inst": "nūru[last part of the night]N",
                  "sig": "@adsd/adart3%akk:ZALAG₂=nūru[light//last part of the night]N'N$nūru",
                  "f": {
                    "lang": "akk",
                    "form": "ZALAG₂",
                    "delim": "",
                    "gdl": [
                      {
                        "gg": "logo",
                        "gdl_type": "logo",
                        "group": [
                          {
                            "s": "ZALAG₂",
                            "id": "X300932.5.21.0",
                            "role": "logo",
                            "logolang": "sux"
                          }
                        ]
                      }
                    ],
                    "cf": "nūru",
                    "gw": "light",
                    "sense": "last part of the night",
                    "norm": "nūru",
                    "pos": "N",
                    "epos": "N"
                  }
                },
                {
                  "node": "l",
                  "frag": "[...]",
                  "id": "X300932.l03a6b",
                  "ref": "X300932.5.22",
                  "inst": "u",
                  "f": {
                    "lang": "akk",
                    "form": "x",
                    "gdl": [
                      {
                        "x": "ellipsis",
                        "id": "X300932.5.22.0",
                        "breakStart": "1",
                        "break": "missing",
                        "o": "]",
                        "breakEnd": "X300932.5.22.0"
                      }
                    ],
                    "pos": "u"
                  }
                },
                {
                  "node": "d",
                  "type": "line-start",
                  "ref": "X300932.6",
                  "n": "5'",
                  "label": "o 5'"
                },
                {
                  "node": "l",
                  "frag": "[...]",
                  "id": "X300932.l03a6c",
                  "ref": "X300932.6.1",
                  "inst": "u",
                  "f": {
                    "lang": "akk",
                    "form": "x",
                    "delim": "",
                    "gdl": [
                      {
                        "x": "ellipsis",
                        "id": "X300932.6.1.0",
                        "breakStart": "1",
                        "break": "missing",
                        "o": "]",
                        "breakEnd": "X300932.6.1.0"
                      }
                    ],
                    "pos": "u"
                  }
                },
                {
                  "node": "l",
                  "frag": "GE₆",
                  "id": "X300932.l03a6d",
                  "ref": "X300932.6.2",
                  "inst": "mūšu[night]N",
                  "sig": "@adsd/adart3%akk:GE₆=mūšu[night//night]N'N$mūšu",
                  "f": {
                    "lang": "akk",
                    "form": "GE₆",
                    "delim": "",
                    "gdl": [
                      {
                        "gg": "logo",
                        "gdl_type": "logo",
                        "group": [
                          {
                            "s": "GE₆",
                            "id": "X300932.6.2.0",
                            "role": "logo",
                            "logolang": "sux"
                          }
                        ]
                      }
                    ],
                    "cf": "mūšu",
                    "gw": "night",
                    "sense": "night",
                    "norm": "mūšu",
                    "pos": "N",
                    "epos": "N"
                  }
                },
                {
                  "node": "l",
                  "frag": "26",
                  "id": "X300932.l03a6e",
                  "ref": "X300932.6.3",
                  "inst": "n",
                  "f": {
                    "lang": "akk",
                    "form": "26",
                    "delim": "",
                    "gdl": [
                      {
                        "n": "n",
                        "sexified": "2(u) 6(diš)",
                        "form": "26",
                        "id": "X300932.6.3.0",
                        "seq": [
                          {
                            "r": "26"
                          }
                        ]
                      }
                    ],
                    "pos": "n"
                  }
                },
                {
                  "node": "l",
                  "frag": "ina",
                  "id": "X300932.l03a6f",
                  "ref": "X300932.6.4",
                  "inst": "ina[in]PRP",
                  "sig": "@adsd/adart3%akk:ina=ina[in//in]PRP'PRP$ina",
                  "f": {
                    "lang": "akk",
                    "form": "ina",
                    "delim": "",
                    "gdl": [
                      {
                        "v": "ina",
                        "id": "X300932.6.4.0"
                      }
                    ],
                    "cf": "ina",
                    "gw": "in",
                    "sense": "in",
                    "norm": "ina",
                    "pos": "PRP",
                    "epos": "PRP"
                  }
                },
                {
                  "node": "l",
                  "frag": "ZALAG₂",
                  "id": "X300932.l03a70",
                  "ref": "X300932.6.5",
                  "inst": "nūru[last part of the night]N",
                  "sig": "@adsd/adart3%akk:ZALAG₂=nūru[light//last part of the night]N'N$nūru",
                  "f": {
                    "lang": "akk",
                    "form": "ZALAG₂",
                    "delim": "",
                    "gdl": [
                      {
                        "gg": "logo",
                        "gdl_type": "logo",
                        "group": [
                          {
                            "s": "ZALAG₂",
                            "id": "X300932.6.5.0",
                            "role": "logo",
                            "logolang": "sux"
                          }
                        ]
                      }
                    ],
                    "cf": "nūru",
                    "gw": "light",
                    "sense": "last part of the night",
                    "norm": "nūru",
                    "pos": "N",
                    "epos": "N"
                  }
                },
                {
                  "node": "l",
                  "frag": "sin",
                  "id": "X300932.l03a71",
                  "ref": "X300932.6.6",
                  "inst": "Sîn[moon]N",
                  "sig": "@adsd/adart3%akk:sin=Sîn[moon(-god)//moon]N'N$Sîn",
                  "f": {
                    "lang": "akk",
                    "form": "sin",
                    "delim": "",
                    "gdl": [
                      {
                        "v": "sin",
                        "id": "X300932.6.6.0"
                      }
                    ],
                    "cf": "Sîn",
                    "gw": "moon(-god)",
                    "sense": "moon",
                    "norm": "Sîn",
                    "pos": "N",
                    "epos": "N"
                  }
                },
                {
                  "node": "c",
                  "type": "phrase",
                  "tag": "phr",
                  "id": "X300932.U5",
                  "ref": "X300932.ls00001",
                  "cdl": [
                    {
                      "node": "l",
                      "frag": "ina",
                      "id": "X300932.l03a72",
                      "ref": "X300932.6.7",
                      "inst": "ina[in]PRP",
                      "sig": "@adsd/adart3%akk:ina=ina[in//in]PRP'PRP$ina",
                      "f": {
                        "lang": "akk",
                        "form": "ina",
                        "delim": "",
                        "gdl": [
                          {
                            "v": "ina",
                            "id": "X300932.6.7.0"
                          }
                        ],
                        "cf": "ina",
                        "gw": "in",
                        "sense": "in",
                        "norm": "ina",
                        "pos": "PRP",
                        "epos": "PRP"
                      }
                    },
                    {
                      "node": "l",
                      "frag": "IGI",
                      "id": "X300932.l03a73",
                      "ref": "X300932.6.8",
                      "inst": "pān[front]N",
                      "sig": "@adsd/adart3%akk:IGI=pānu[front//front]N'N$pān",
                      "f": {
                        "lang": "akk",
                        "form": "IGI",
                        "delim": "",
                        "gdl": [
                          {
                            "gg": "logo",
                            "gdl_type": "logo",
                            "group": [
                              {
                                "s": "IGI",
                                "id": "X300932.6.8.0",
                                "role": "logo",
                                "logolang": "sux"
                              }
                            ]
                          }
                        ],
                        "cf": "pānu",
                        "gw": "front",
                        "sense": "front",
                        "norm": "pān",
                        "pos": "N",
                        "epos": "N"
                      }
                    }
                  ]
                },
                {
                  "node": "l",
                  "frag": "MAŠ.MAŠ-ar₂",
                  "id": "X300932.l03a74",
                  "ref": "X300932.6.9",
                  "inst": "MAŠ.MAŠ-ár[β Geminorum]CN",
                  "sig": "@adsd/adart3%akk:MAŠ.MAŠ-ar₂=MAŠ.MAŠ-ár[β Geminorum//β Geminorum]CN'CN$MAŠ.MAŠ-ár",
                  "f": {
                    "lang": "akk",
                    "form": "MAŠ.MAŠ-ar₂",
                    "delim": "",
                    "gdl": [
                      {
                        "gg": "logo",
                        "gdl_type": "logo",
                        "group": [
                          {
                            "s": "MAŠ",
                            "id": "X300932.6.9.0",
                            "role": "logo",
                            "logolang": "sux",
                            "delim": "."
                          },
                          {
                            "s": "MAŠ",
                            "id": "X300932.6.9.1",
                            "role": "logo",
                            "logolang": "sux",
                            "delim": "-"
                          }
                        ]
                      },
                      {
                        "v": "ar₂",
                        "id": "X300932.6.9.2"
                      }
                    ],
                    "cf": "MAŠ.MAŠ-ár",
                    "gw": "β Geminorum",
                    "sense": "β Geminorum",
                    "norm": "MAŠ.MAŠ-ár",
                    "pos": "CN",
                    "epos": "CN"
                  }
                },
                {
                  "node": "l",
                  "frag": "1",
                  "id": "X300932.l03a75",
                  "ref": "X300932.6.10",
                  "inst": "n",
                  "f": {
                    "lang": "akk",
                    "form": "1",
                    "delim": "",
                    "gdl": [
                      {
                        "n": "n",
                        "sexified": "1(diš)",
                        "form": "1",
                        "id": "X300932.6.10.0",
                        "seq": [
                          {
                            "r": "1"
                          }
                        ]
                      }
                    ],
                    "pos": "n"
                  }
                },
                {
                  "node": "l",
                  "frag": "KUŠ₃",
                  "id": "X300932.l03a76",
                  "ref": "X300932.6.11",
                  "inst": "ammatu[unit]N",
                  "sig": "@adsd/adart3%akk:KUŠ₃=ammatu[unit//unit]N'N$ammatu",
                  "f": {
                    "lang": "akk",
                    "form": "KUŠ₃",
                    "delim": "",
                    "gdl": [
                      {
                        "gg": "logo",
                        "gdl_type": "logo",
                        "group": [
                          {
                            "s": "KUŠ₃",
                            "id": "X300932.6.11.0",
                            "role": "logo",
                            "logolang": "sux"
                          }
                        ]
                      }
                    ],
                    "cf": "ammatu",
                    "gw": "unit",
                    "sense": "unit",
                    "norm": "ammatu",
                    "pos": "N",
                    "epos": "N"
                  }
                },
                {
                  "node": "l",
                  "frag": "⸢sin⸣",
                  "id": "X300932.l03a77",
                  "ref": "X300932.6.12",
                  "inst": "Sîn[moon]N",
                  "sig": "@adsd/adart3%akk:sin=Sîn[moon(-god)//moon]N'N$Sîn",
                  "f": {
                    "lang": "akk",
                    "form": "sin",
                    "delim": "",
                    "gdl": [
                      {
                        "v": "sin",
                        "id": "X300932.6.12.0",
                        "break": "damaged",
                        "ho": "1",
                        "hc": "1"
                      }
                    ],
                    "cf": "Sîn",
                    "gw": "moon(-god)",
                    "sense": "moon",
                    "norm": "Sîn",
                    "pos": "N",
                    "epos": "N"
                  }
                },
                {
                  "node": "l",
                  "frag": "[...]",
                  "id": "X300932.l03a78",
                  "ref": "X300932.6.13",
                  "inst": "u",
                  "f": {
                    "lang": "akk",
                    "form": "x",
                    "gdl": [
                      {
                        "x": "ellipsis",
                        "id": "X300932.6.13.0",
                        "breakStart": "1",
                        "break": "missing",
                        "o": "]",
                        "breakEnd": "X300932.6.13.0"
                      }
                    ],
                    "pos": "u"
                  }
                },
                {
                  "node": "d",
                  "type": "line-start",
                  "ref": "X300932.7",
                  "n": "6'",
                  "label": "o 6'"
                },
                {
                  "node": "l",
                  "frag": "[...",
                  "id": "X300932.l03a79",
                  "ref": "X300932.7.1",
                  "inst": "u",
                  "f": {
                    "lang": "akk",
                    "form": "x",
                    "delim": "",
                    "gdl": [
                      {
                        "x": "ellipsis",
                        "id": "X300932.7.1.0",
                        "breakStart": "1",
                        "break": "missing",
                        "o": "["
                      }
                    ],
                    "pos": "u"
                  }
                },
                {
                  "node": "l",
                  "frag": "ina",
                  "id": "X300932.l03a7a",
                  "ref": "X300932.7.2",
                  "inst": "ina[in]PRP",
                  "sig": "@adsd/adart3%akk:ina=ina[in//in]PRP'PRP$ina",
                  "f": {
                    "lang": "akk",
                    "form": "ina",
                    "delim": "",
                    "gdl": [
                      {
                        "v": "ina",
                        "id": "X300932.7.2.0",
                        "break": "missing"
                      }
                    ],
                    "cf": "ina",
                    "gw": "in",
                    "sense": "in",
                    "norm": "ina",
                    "pos": "PRP",
                    "epos": "PRP"
                  }
                },
                {
                  "node": "l",
                  "frag": "TIL]",
                  "id": "X300932.l03a7b",
                  "ref": "X300932.7.3",
                  "inst": "qītu[end]N",
                  "sig": "@adsd/adart3%akk:TIL=qītu[end//end]N'N$qītu",
                  "f": {
                    "lang": "akk",
                    "form": "TIL",
                    "delim": "",
                    "gdl": [
                      {
                        "gg": "logo",
                        "gdl_type": "logo",
                        "group": [
                          {
                            "s": "TIL",
                            "id": "X300932.7.3.0",
                            "break": "missing",
                            "role": "logo",
                            "logolang": "sux",
                            "o": "]",
                            "breakEnd": "X300932.7.1.0"
                          }
                        ]
                      }
                    ],
                    "cf": "qītu",
                    "gw": "end",
                    "sense": "end",
                    "norm": "qītu",
                    "pos": "N",
                    "epos": "N"
                  }
                },
                {
                  "node": "l",
                  "frag": "⸢ITU⸣",
                  "id": "X300932.l03a7c",
                  "ref": "X300932.7.4",
                  "inst": "warhu[month]N",
                  "sig": "@adsd/adart3%akk:ITU=warhu[month//month]N'N$warhu",
                  "f": {
                    "lang": "akk",
                    "form": "ITU",
                    "delim": "",
                    "gdl": [
                      {
                        "gg": "logo",
                        "gdl_type": "logo",
                        "group": [
                          {
                            "s": "ITU",
                            "id": "X300932.7.4.0",
                            "break": "damaged",
                            "ho": "1",
                            "role": "logo",
                            "logolang": "sux",
                            "hc": "1"
                          }
                        ]
                      }
                    ],
                    "cf": "warhu",
                    "gw": "month",
                    "sense": "month",
                    "norm": "warhu",
                    "pos": "N",
                    "epos": "N"
                  }
                },
                {
                  "node": "l",
                  "frag": "2(BARIG)",
                  "id": "X300932.l03a7d",
                  "ref": "X300932.7.5",
                  "inst": "n",
                  "f": {
                    "lang": "akk",
                    "form": "2(BARIG)",
                    "delim": "",
                    "gdl": [
                      {
                        "n": "n",
                        "form": "2(BARIG)",
                        "id": "X300932.7.5.0",
                        "seq": [
                          {
                            "r": "2"
                          },
                          {
                            "s": "BARIG"
                          }
                        ]
                      }
                    ],
                    "pos": "n"
                  }
                },
                {
                  "node": "l",
                  "frag": "5(BAN₂)",
                  "id": "X300932.l03a7e",
                  "ref": "X300932.7.6",
                  "inst": "n",
                  "f": {
                    "lang": "akk",
                    "form": "5(BAN₂)",
                    "delim": "",
                    "gdl": [
                      {
                        "n": "n",
                        "form": "5(BAN₂)",
                        "id": "X300932.7.6.0",
                        "seq": [
                          {
                            "r": "5"
                          },
                          {
                            "s": "BAN₂"
                          }
                        ]
                      }
                    ],
                    "pos": "n"
                  }
                },
                {
                  "node": "l",
                  "frag": "NU",
                  "id": "X300932.l03a7f",
                  "ref": "X300932.7.7",
                  "inst": "ul[not]MOD",
                  "sig": "@adsd/adart3%akk:NU=ul[not//not]MOD'MOD$ul",
                  "f": {
                    "lang": "akk",
                    "form": "NU",
                    "delim": "",
                    "gdl": [
                      {
                        "gg": "logo",
                        "gdl_type": "logo",
                        "group": [
                          {
                            "s": "NU",
                            "id": "X300932.7.7.0",
                            "role": "logo",
                            "logolang": "sux"
                          }
                        ]
                      }
                    ],
                    "cf": "ul",
                    "gw": "not",
                    "sense": "not",
                    "norm": "ul",
                    "pos": "MOD",
                    "epos": "MOD"
                  }
                },
                {
                  "node": "l",
                  "frag": "DU₃-tu₂",
                  "id": "X300932.l03a80",
                  "ref": "X300932.7.8",
                  "inst": "banītu[good]AJ",
                  "sig": "@adsd/adart3%akk:DU₃-tu₂=banû[good//good]AJ'AJ$banītu",
                  "f": {
                    "lang": "akk",
                    "form": "DU₃-tu₂",
                    "delim": "",
                    "gdl": [
                      {
                        "gg": "logo",
                        "gdl_type": "logo",
                        "group": [
                          {
                            "s": "DU₃",
                            "id": "X300932.7.8.0",
                            "role": "logo",
                            "logolang": "sux",
                            "delim": "-"
                          }
                        ]
                      },
                      {
                        "v": "tu₂",
                        "id": "X300932.7.8.1"
                      }
                    ],
                    "cf": "banû",
                    "gw": "good",
                    "sense": "good",
                    "norm": "banītu",
                    "pos": "AJ",
                    "epos": "AJ"
                  }
                },
                {
                  "node": "l",
                  "frag": "3(BARIG)",
                  "id": "X300932.l03a81",
                  "ref": "X300932.7.9",
                  "inst": "n",
                  "f": {
                    "lang": "akk",
                    "form": "3(BARIG)",
                    "delim": "",
                    "gdl": [
                      {
                        "n": "n",
                        "form": "3(BARIG)",
                        "id": "X300932.7.9.0",
                        "seq": [
                          {
                            "r": "3"
                          },
                          {
                            "s": "BARIG"
                          }
                        ]
                      }
                    ],
                    "pos": "n"
                  }
                },
                {
                  "node": "l",
                  "frag": "4(BAN₂)",
                  "id": "X300932.l03a82",
                  "ref": "X300932.7.10",
                  "inst": "n",
                  "f": {
                    "lang": "akk",
                    "form": "4(BAN₂)",
                    "delim": "",
                    "gdl": [
                      {
                        "n": "n",
                        "form": "4(BAN₂)",
                        "id": "X300932.7.10.0",
                        "seq": [
                          {
                            "r": "4"
                          },
                          {
                            "s": "BAN₂"
                          }
                        ]
                      }
                    ],
                    "pos": "n"
                  }
                },
                {
                  "node": "l",
                  "frag": "3",
                  "id": "X300932.l03a83",
                  "ref": "X300932.7.11",
                  "inst": "n",
                  "f": {
                    "lang": "akk",
                    "form": "3",
                    "delim": "",
                    "gdl": [
                      {
                        "n": "n",
                        "sexified": "3(diš)",
                        "form": "3",
                        "id": "X300932.7.11.0",
                        "seq": [
                          {
                            "r": "3"
                          }
                        ]
                      }
                    ],
                    "pos": "n"
                  }
                },
                {
                  "node": "l",
                  "frag": "qa",
                  "id": "X300932.l03a84",
                  "ref": "X300932.7.12",
                  "inst": "qû[(one) litre]N",
                  "sig": "@adsd/adart3%akk:qa=qû[(one) litre//(one) litre]N'N$qû",
                  "f": {
                    "lang": "akk",
                    "form": "qa",
                    "delim": "",
                    "gdl": [
                      {
                        "v": "qa",
                        "id": "X300932.7.12.0"
                      }
                    ],
                    "cf": "qû",
                    "gw": "(one) litre",
                    "sense": "(one) litre",
                    "norm": "qû",
                    "pos": "N",
                    "epos": "N"
                  }
                },
                {
                  "node": "l",
                  "frag": "[...]",
                  "id": "X300932.l03a85",
                  "ref": "X300932.7.13",
                  "inst": "u",
                  "f": {
                    "lang": "akk",
                    "form": "x",
                    "gdl": [
                      {
                        "x": "ellipsis",
                        "id": "X300932.7.13.0",
                        "breakStart": "1",
                        "break": "missing",
                        "o": "]",
                        "breakEnd": "X300932.7.13.0"
                      }
                    ],
                    "pos": "u"
                  }
                },
                {
                  "node": "d",
                  "type": "line-start",
                  "ref": "X300932.8",
                  "n": "7'",
                  "label": "o 7'"
                },
                {
                  "node": "l",
                  "frag": "[...]",
                  "id": "X300932.l03a86",
                  "ref": "X300932.8.1",
                  "inst": "u",
                  "f": {
                    "lang": "akk",
                    "form": "x",
                    "delim": "",
                    "gdl": [
                      {
                        "x": "ellipsis",
                        "id": "X300932.8.1.0",
                        "breakStart": "1",
                        "break": "missing",
                        "o": "]",
                        "breakEnd": "X300932.8.1.0"
                      }
                    ],
                    "pos": "u"
                  }
                },
                {
                  "node": "l",
                  "frag": "⸢GENNA⸣",
                  "id": "X300932.l03a87",
                  "ref": "X300932.8.2",
                  "inst": "Kayyamānu[Saturn]CN",
                  "sig": "@adsd/adart3%akk:GENNA=Kayyamānu[Saturn//Saturn]CN'CN$Kayyamānu",
                  "f": {
                    "lang": "akk",
                    "form": "GENNA",
                    "delim": "",
                    "gdl": [
                      {
                        "gg": "logo",
                        "gdl_type": "logo",
                        "group": [
                          {
                            "s": "GENNA",
                            "id": "X300932.8.2.0",
                            "break": "damaged",
                            "ho": "1",
                            "role": "logo",
                            "logolang": "sux",
                            "hc": "1"
                          }
                        ]
                      }
                    ],
                    "cf": "Kayyamānu",
                    "gw": "Saturn",
                    "sense": "Saturn",
                    "norm": "Kayyamānu",
                    "pos": "CN",
                    "epos": "CN"
                  }
                },
                {
                  "node": "l",
                  "frag": "ina",
                  "id": "X300932.l03a88",
                  "ref": "X300932.8.3",
                  "inst": "ina[in]PRP",
                  "sig": "@adsd/adart3%akk:ina=ina[in//in]PRP'PRP$ina",
                  "f": {
                    "lang": "akk",
                    "form": "ina",
                    "delim": "",
                    "gdl": [
                      {
                        "v": "ina",
                        "id": "X300932.8.3.0"
                      }
                    ],
                    "cf": "ina",
                    "gw": "in",
                    "sense": "in",
                    "norm": "ina",
                    "pos": "PRP",
                    "epos": "PRP"
                  }
                },
                {
                  "node": "l",
                  "frag": "HUN",
                  "id": "X300932.l03a89",
                  "ref": "X300932.8.4",
                  "inst": "Agru[Aries]CN",
                  "sig": "@adsd/adart3%akk:HUN=Agru[Aries//Aries]CN'CN$Agru",
                  "f": {
                    "lang": "akk",
                    "form": "HUN",
                    "delim": "",
                    "gdl": [
                      {
                        "gg": "logo",
                        "gdl_type": "logo",
                        "group": [
                          {
                            "s": "HUN",
                            "id": "X300932.8.4.0",
                            "role": "logo",
                            "logolang": "sux"
                          }
                        ]
                      }
                    ],
                    "cf": "Agru",
                    "gw": "Aries",
                    "sense": "Aries",
                    "norm": "Agru",
                    "pos": "CN",
                    "epos": "CN"
                  }
                },
                {
                  "node": "l",
                  "frag": "AN",
                  "id": "X300932.l03a8a",
                  "ref": "X300932.8.5",
                  "inst": "Ṣalbaṭānu[Mars]CN",
                  "sig": "@adsd/adart3%akk:AN=Ṣalbaṭānu[Mars//Mars]CN'CN$Ṣalbaṭānu",
                  "f": {
                    "lang": "akk",
                    "form": "AN",
                    "delim": "",
                    "gdl": [
                      {
                        "gg": "logo",
                        "gdl_type": "logo",
                        "group": [
                          {
                            "s": "AN",
                            "id": "X300932.8.5.0",
                            "role": "logo",
                            "logolang": "sux"
                          }
                        ]
                      }
                    ],
                    "cf": "Ṣalbaṭānu",
                    "gw": "Mars",
                    "sense": "Mars",
                    "norm": "Ṣalbaṭānu",
                    "pos": "CN",
                    "epos": "CN"
                  }
                },
                {
                  "node": "l",
                  "frag": "ina",
                  "id": "X300932.l03a8b",
                  "ref": "X300932.8.6",
                  "inst": "ina[in]PRP",
                  "sig": "@adsd/adart3%akk:ina=ina[in//in]PRP'PRP$ina",
                  "f": {
                    "lang": "akk",
                    "form": "ina",
                    "delim": "",
                    "gdl": [
                      {
                        "v": "ina",
                        "id": "X300932.8.6.0"
                      }
                    ],
                    "cf": "ina",
                    "gw": "in",
                    "sense": "in",
                    "norm": "ina",
                    "pos": "PRP",
                    "epos": "PRP"
                  }
                },
                {
                  "node": "l",
                  "frag": "A",
                  "id": "X300932.l03a8c",
                  "ref": "X300932.8.7",
                  "inst": "Nēšu[Leo]CN",
                  "sig": "@adsd/adart3%akk:A=Nēšu[Leo//Leo]CN'CN$Nēšu",
                  "f": {
                    "lang": "akk",
                    "form": "A",
                    "delim": "",
                    "gdl": [
                      {
                        "gg": "logo",
                        "gdl_type": "logo",
                        "group": [
                          {
                            "s": "A",
                            "id": "X300932.8.7.0",
                            "role": "logo",
                            "logolang": "sux"
                          }
                        ]
                      }
                    ],
                    "cf": "Nēšu",
                    "gw": "Leo",
                    "sense": "Leo",
                    "norm": "Nēšu",
                    "pos": "CN",
                    "epos": "CN"
                  }
                },
                {
                  "node": "l",
                  "frag": "in",
                  "id": "X300932.l03a8d",
                  "ref": "X300932.8.8",
                  "inst": "ina[around (day x)]PRP",
                  "sig": "@adsd/adart3%akk:in=ina[in//around (day x)]PRP'PRP$ina",
                  "f": {
                    "lang": "akk",
                    "form": "in",
                    "delim": "",
                    "gdl": [
                      {
                        "v": "in",
                        "id": "X300932.8.8.0"
                      }
                    ],
                    "cf": "ina",
                    "gw": "in",
                    "sense": "around (day x)",
                    "norm": "ina",
                    "pos": "PRP",
                    "epos": "PRP"
                  }
                },
                {
                  "node": "l",
                  "frag": "17",
                  "id": "X300932.l03a8e",
                  "ref": "X300932.8.9",
                  "inst": "n",
                  "f": {
                    "lang": "akk",
                    "form": "17",
                    "delim": "",
                    "gdl": [
                      {
                        "n": "n",
                        "sexified": "1(u) 7(diš)",
                        "form": "17",
                        "id": "X300932.8.9.0",
                        "seq": [
                          {
                            "r": "17"
                          }
                        ]
                      }
                    ],
                    "pos": "n"
                  }
                },
                {
                  "node": "l",
                  "frag": "⸢AN⸣",
                  "id": "X300932.l03a8f",
                  "ref": "X300932.8.10",
                  "inst": "Ṣalbaṭānu[Mars]CN",
                  "sig": "@adsd/adart3%akk:AN=Ṣalbaṭānu[Mars//Mars]CN'CN$Ṣalbaṭānu",
                  "f": {
                    "lang": "akk",
                    "form": "AN",
                    "delim": "",
                    "gdl": [
                      {
                        "gg": "logo",
                        "gdl_type": "logo",
                        "group": [
                          {
                            "s": "AN",
                            "id": "X300932.8.10.0",
                            "break": "damaged",
                            "ho": "1",
                            "role": "logo",
                            "logolang": "sux",
                            "hc": "1"
                          }
                        ]
                      }
                    ],
                    "cf": "Ṣalbaṭānu",
                    "gw": "Mars",
                    "sense": "Mars",
                    "norm": "Ṣalbaṭānu",
                    "pos": "CN",
                    "epos": "CN"
                  }
                },
                {
                  "node": "l",
                  "frag": "[...",
                  "id": "X300932.l03a90",
                  "ref": "X300932.8.11",
                  "inst": "u",
                  "f": {
                    "lang": "akk",
                    "form": "x",
                    "delim": "",
                    "gdl": [
                      {
                        "x": "ellipsis",
                        "id": "X300932.8.11.0",
                        "breakStart": "1",
                        "break": "missing",
                        "o": "["
                      }
                    ],
                    "pos": "u"
                  }
                },
                {
                  "node": "l",
                  "frag": "ŠU₂",
                  "id": "X300932.l03a91",
                  "ref": "X300932.8.12",
                  "inst": "rabû[set]'V",
                  "sig": "@adsd/adart3%akk:ŠU₂=rabû[set//set]V'V$rabû",
                  "f": {
                    "lang": "akk",
                    "form": "ŠU₂",
                    "delim": "",
                    "gdl": [
                      {
                        "gg": "logo",
                        "gdl_type": "logo",
                        "group": [
                          {
                            "s": "ŠU₂",
                            "id": "X300932.8.12.0",
                            "break": "missing",
                            "role": "logo",
                            "logolang": "sux"
                          }
                        ]
                      }
                    ],
                    "cf": "rabû",
                    "gw": "set",
                    "sense": "set",
                    "norm": "rabû",
                    "pos": "V",
                    "epos": "V"
                  }
                },
                {
                  "node": "l",
                  "frag": "...]",
                  "id": "X300932.l03a92",
                  "ref": "X300932.8.13",
                  "inst": "u",
                  "f": {
                    "lang": "akk",
                    "form": "x",
                    "gdl": [
                      {
                        "x": "ellipsis",
                        "id": "X300932.8.13.0",
                        "break": "missing",
                        "o": "]",
                        "breakEnd": "X300932.8.11.0"
                      }
                    ],
                    "pos": "u"
                  }
                },
                {
                  "node": "d",
                  "type": "line-start",
                  "ref": "X300932.9",
                  "n": "8'",
                  "label": "o 8'"
                },
                {
                  "node": "l",
                  "frag": "[...]",
                  "id": "X300932.l03a93",
                  "ref": "X300932.9.1",
                  "inst": "u",
                  "f": {
                    "lang": "akk",
                    "form": "x",
                    "delim": "",
                    "gdl": [
                      {
                        "x": "ellipsis",
                        "id": "X300932.9.1.0",
                        "breakStart": "1",
                        "break": "missing",
                        "o": "]",
                        "breakEnd": "X300932.9.1.0"
                      }
                    ],
                    "pos": "u"
                  }
                },
                {
                  "node": "l",
                  "frag": "⸢E₃⸣-a",
                  "id": "X300932.l03a94",
                  "ref": "X300932.9.2",
                  "inst": "elû[rise]V",
                  "sig": "@adsd/adart3%akk:E₃-a=elû[go up//rise]V'V$elû",
                  "f": {
                    "lang": "akk",
                    "form": "E₃-a",
                    "delim": "",
                    "gdl": [
                      {
                        "gg": "logo",
                        "gdl_type": "logo",
                        "group": [
                          {
                            "s": "E₃",
                            "id": "X300932.9.2.0",
                            "break": "damaged",
                            "ho": "1",
                            "role": "logo",
                            "logolang": "sux",
                            "delim": "-",
                            "hc": "1"
                          }
                        ]
                      },
                      {
                        "v": "a",
                        "id": "X300932.9.2.1"
                      }
                    ],
                    "cf": "elû",
                    "gw": "go up",
                    "sense": "rise",
                    "norm": "elû",
                    "pos": "V",
                    "epos": "V"
                  }
                },
                {
                  "node": "l",
                  "frag": "ITU",
                  "id": "X300932.l03a95",
                  "ref": "X300932.9.3",
                  "inst": "warhu[month]N",
                  "sig": "@adsd/adart3%akk:ITU=warhu[month//month]N'N$warhu",
                  "f": {
                    "lang": "akk",
                    "form": "ITU",
                    "delim": "",
                    "gdl": [
                      {
                        "gg": "logo",
                        "gdl_type": "logo",
                        "group": [
                          {
                            "s": "ITU",
                            "id": "X300932.9.3.0",
                            "role": "logo",
                            "logolang": "sux"
                          }
                        ]
                      }
                    ],
                    "cf": "warhu",
                    "gw": "month",
                    "sense": "month",
                    "norm": "warhu",
                    "pos": "N",
                    "epos": "N"
                  }
                },
                {
                  "node": "l",
                  "frag": "BI",
                  "id": "X300932.l03a96",
                  "ref": "X300932.9.4",
                  "inst": "šū[that]'DP",
                  "sig": "@adsd/adart3%akk:BI=šū[he//that]IP'DP$šū",
                  "f": {
                    "lang": "akk",
                    "form": "BI",
                    "delim": "",
                    "gdl": [
                      {
                        "gg": "logo",
                        "gdl_type": "logo",
                        "group": [
                          {
                            "s": "BI",
                            "id": "X300932.9.4.0",
                            "role": "logo",
                            "logolang": "sux"
                          }
                        ]
                      }
                    ],
                    "cf": "šū",
                    "gw": "he",
                    "sense": "that",
                    "norm": "šū",
                    "pos": "IP",
                    "epos": "DP"
                  }
                },
                {
                  "node": "l",
                  "frag": "⸢GIG⸣{meš}",
                  "id": "X300932.l03a97",
                  "ref": "X300932.9.5",
                  "inst": "murṣu[illness]N",
                  "sig": "@adsd/adart3%akk:GIG{MEŠ}=murṣu[illness//illness]N'N$murṣu",
                  "f": {
                    "lang": "akk",
                    "form": "GIG{MEŠ}",
                    "delim": "",
                    "gdl": [
                      {
                        "gg": "logo",
                        "gdl_type": "logo",
                        "group": [
                          {
                            "s": "GIG",
                            "id": "X300932.9.5.0",
                            "break": "damaged",
                            "queried": "1",
                            "ho": "1",
                            "role": "logo",
                            "logolang": "sux",
                            "hc": "1"
                          },
                          {
                            "det": "semantic",
                            "pos": "post",
                            "seq": [
                              {
                                "s": "MEŠ",
                                "id": "X300932.9.5.1",
                                "role": "logo",
                                "logolang": "sux"
                              }
                            ]
                          }
                        ]
                      }
                    ],
                    "cf": "murṣu",
                    "gw": "illness",
                    "sense": "illness",
                    "norm": "murṣu",
                    "pos": "N",
                    "epos": "N"
                  }
                },
                {
                  "node": "l",
                  "frag": "[...]",
                  "id": "X300932.l03a98",
                  "ref": "X300932.9.6",
                  "inst": "u",
                  "f": {
                    "lang": "akk",
                    "form": "x",
                    "gdl": [
                      {
                        "x": "ellipsis",
                        "id": "X300932.9.6.0",
                        "breakStart": "1",
                        "break": "missing",
                        "o": "]",
                        "breakEnd": "X300932.9.6.0"
                      }
                    ],
                    "pos": "u"
                  }
                },
                {
                  "node": "d",
                  "type": "line-start",
                  "ref": "X300932.10",
                  "n": "9'",
                  "label": "o 9'"
                },
                {
                  "node": "l",
                  "frag": "[...",
                  "id": "X300932.l03a99",
                  "ref": "X300932.10.1",
                  "inst": "u",
                  "f": {
                    "lang": "akk",
                    "form": "x",
                    "delim": "",
                    "gdl": [
                      {
                        "x": "ellipsis",
                        "id": "X300932.10.1.0",
                        "breakStart": "1",
                        "break": "missing",
                        "o": "["
                      }
                    ],
                    "pos": "u"
                  }
                },
                {
                  "node": "l",
                  "frag": "{id₂]}⸢BURANUN⸣{ki}",
                  "id": "X300932.l03a9a",
                  "ref": "X300932.10.2",
                  "inst": "Purattu[Euphrates]WN",
                  "sig": "@adsd/adart3%akk:{ID₂}BURANUN{KI}=Purattu[Euphrates//Euphrates]WN'WN$Purattu",
                  "f": {
                    "lang": "akk",
                    "form": "{ID₂}BURANUN{KI}",
                    "delim": "",
                    "gdl": [
                      {
                        "gg": "logo",
                        "gdl_type": "logo",
                        "group": [
                          {
                            "det": "semantic",
                            "pos": "pre",
                            "seq": [
                              {
                                "gg": "logo",
                                "gdl_type": "logo",
                                "group": [
                                  {
                                    "s": "ID₂",
                                    "id": "X300932.10.2.0",
                                    "break": "missing",
                                    "role": "logo",
                                    "logolang": "sux",
                                    "o": "]",
                                    "breakEnd": "X300932.10.1.0"
                                  }
                                ]
                              }
                            ]
                          },
                          {
                            "s": "BURANUN",
                            "id": "X300932.10.2.1",
                            "break": "damaged",
                            "ho": "1",
                            "role": "logo",
                            "logolang": "sux",
                            "hc": "1"
                          },
                          {
                            "det": "semantic",
                            "pos": "post",
                            "seq": [
                              {
                                "s": "KI",
                                "id": "X300932.10.2.2",
                                "role": "logo",
                                "logolang": "sux"
                              }
                            ]
                          }
                        ]
                      }
                    ],
                    "cf": "Purattu",
                    "gw": "Euphrates",
                    "sense": "Euphrates",
                    "norm": "Purattu",
                    "pos": "WN",
                    "epos": "WN"
                  }
                },
                {
                  "node": "l",
                  "frag": "i-[na",
                  "id": "X300932.l03a9b",
                  "ref": "X300932.10.3",
                  "inst": "X",
                  "f": {
                    "lang": "akk",
                    "form": "i-na",
                    "delim": "",
                    "gdl": [
                      {
                        "v": "i",
                        "id": "X300932.10.3.0",
                        "delim": "-"
                      },
                      {
                        "v": "na",
                        "id": "X300932.10.3.1",
                        "breakStart": "1",
                        "o": "[",
                        "break": "missing"
                      }
                    ],
                    "pos": "X"
                  }
                },
                {
                  "node": "l",
                  "frag": "...]",
                  "id": "X300932.l03a9c",
                  "ref": "X300932.10.4",
                  "inst": "u",
                  "f": {
                    "lang": "akk",
                    "form": "x",
                    "gdl": [
                      {
                        "x": "ellipsis",
                        "id": "X300932.10.4.0",
                        "break": "missing",
                        "o": "]",
                        "breakEnd": "X300932.10.3.1"
                      }
                    ],
                    "pos": "u"
                  }
                },
                {
                  "node": "d",
                  "type": "line-start",
                  "ref": "X300932.11",
                  "n": "10'",
                  "label": "o 10'"
                },
                {
                  "node": "l",
                  "frag": "[...]",
                  "id": "X300932.l03a9d",
                  "ref": "X300932.11.1",
                  "inst": "u",
                  "f": {
                    "lang": "akk",
                    "form": "x",
                    "delim": "",
                    "gdl": [
                      {
                        "x": "ellipsis",
                        "id": "X300932.11.1.0",
                        "breakStart": "1",
                        "break": "missing",
                        "o": "]",
                        "breakEnd": "X300932.11.1.0"
                      }
                    ],
                    "pos": "u"
                  }
                },
                {
                  "node": "d",
                  "frag": "($blank$)",
                  "type": "dollar",
                  "ref": "X300932.11.2"
                },
                {
                  "node": "l",
                  "frag": "[...]",
                  "id": "X300932.l03a9e",
                  "ref": "X300932.11.3",
                  "inst": "u",
                  "f": {
                    "lang": "akk",
                    "form": "x",
                    "gdl": [
                      {
                        "x": "ellipsis",
                        "id": "X300932.11.3.0",
                        "breakStart": "1",
                        "break": "missing",
                        "o": "]",
                        "breakEnd": "X300932.11.3.0"
                      }
                    ],
                    "pos": "u"
                  }
                }
              ]
            }
          ]
        }
      ]
    },
    {
      "linkbase": [
        {
          "type": "linkset",
          "xlink_title": "mūšu alāku[after sunset//after sunset]N'N",
          "id": "X300932.ls00000",
          "xlink_type": "extended",
          "xlink_role": "psu",
          "sig": "{GE₆ GIN = mūšu[night]N alāku[go]V += mūšu alāku[after sunset//after sunset]N'N}::@adsd/adart3%akk:GE₆=mūšu[night//night]N'N$mūšu++@adsd/adart3%akk:GIN=alāku[go//go]V'V$alāku",
          "links": [
            {
              "type": "link",
              "xlink_title": "mūšu",
              "xlink_type": "locator",
              "xlink_href": "#X300932.l03a4a",
              "xlink_role": "elt"
            },
            {
              "type": "link",
              "xlink_title": "alāku",
              "xlink_type": "locator",
              "xlink_href": "#X300932.l03a4b",
              "xlink_role": "elt"
            }
          ]
        },
        {
          "type": "linkset",
          "xlink_title": "ina pān[in front of//in front of]PRP'PRP",
          "id": "X300932.ls00001",
          "xlink_type": "extended",
          "xlink_role": "psu",
          "sig": "{ina IGI = ina[in]PRP pānu[front]N += ina pān[in front of//in front of]PRP'PRP}::@adsd/adart3%akk:ina=ina[in//in]PRP'PRP$ina++@adsd/adart3%akk:IGI=pānu[front//front]N'N$pān",
          "links": [
            {
              "type": "link",
              "xlink_title": "ina",
              "xlink_type": "locator",
              "xlink_href": "#X300932.l03a72",
              "xlink_role": "elt"
            },
            {
              "type": "link",
              "xlink_title": "pān",
              "xlink_type": "locator",
              "xlink_href": "#X300932.l03a73",
              "xlink_role": "elt"
            }
          ]
        }
      ]
    }
  ]
}
